libcgroup/__init__.py
libcgroup/cgroup.py
libcgroup/mount_point.py
libcgroup/tools.py
test2/__init__.py
test2/test_cgroup.py
libcgroup-0.2.4.dist-info/COPYING
libcgroup-0.2.4.dist-info/COPYING.LESSER
libcgroup-0.2.4.dist-info/METADATA
libcgroup-0.2.4.dist-info/WHEEL
libcgroup-0.2.4.dist-info/top_level.txt
libcgroup-0.2.4.dist-info/RECORD
