Metadata-Version: 2.1
Name: libcgroup
Version: 0.2.4
Summary: A library that handles Linux cgroups internally using the libcgroup shared library.
Home-page: https://github.com/isac322/python-libcgroup
Author: Byeonghoon Yoo
Author-email: bh322yoo@gmail.com
License: LGPLv3+
Keywords: Linux cgroup libcgroup control_group
Platform: Linux
Classifier: Development Status :: 3 - Alpha
Classifier: Environment :: No Input/Output (Daemon)
Classifier: Intended Audience :: Developers
Classifier: License :: OSI Approved :: GNU Lesser General Public License v3 or later (LGPLv3+)
Classifier: Natural Language :: English
Classifier: Operating System :: POSIX :: Linux
Classifier: Programming Language :: Python :: 3
Classifier: Programming Language :: Python :: 3.6
Classifier: Programming Language :: Python :: 3.7
Classifier: Programming Language :: Python :: 3 :: Only
Classifier: Programming Language :: Python :: Implementation
Classifier: Programming Language :: Python :: Implementation :: CPython
Classifier: Programming Language :: Python :: Implementation :: PyPy
Classifier: Programming Language :: Python :: Implementation :: Stackless
Classifier: Topic :: Software Development
Classifier: Topic :: Software Development :: Embedded Systems
Classifier: Topic :: Software Development :: Libraries
Classifier: Topic :: Software Development :: Libraries :: Python Modules
Classifier: Topic :: System
Classifier: Topic :: System :: Filesystems
Classifier: Topic :: System :: Operating System
Classifier: Topic :: System :: Operating System Kernels
Classifier: Topic :: System :: Operating System Kernels :: Linux
Classifier: Typing :: Typed
Provides: libcgroup
Requires-Python: >=3.6
Requires-Dist: libcgroup-bind
Provides-Extra: stub
Requires-Dist: typing ; extra == 'stub'
